{
  "schemaVersion": 1,
  "surface": "provider-facts",
  "service": "mysql",
  "slug": "mysqlmysqlconfiguration",
  "kind": "MysqlMysqlConfiguration",
  "sourceRef": "terraform-provider-oci",
  "providerResource": "oci_mysql_mysql_configuration",
  "operations": {
    "create": [
      {
        "operation": "CreateMysqlMysqlConfiguration",
        "requestType": "mysql.CreateMysqlMysqlConfigurationRequest",
        "responseType": "mysql.CreateMysqlMysqlConfigurationResponse"
      }
    ],
    "get": [
      {
        "operation": "GetMysqlMysqlConfiguration",
        "requestType": "mysql.GetMysqlMysqlConfigurationRequest",
        "responseType": "mysql.GetMysqlMysqlConfigurationResponse"
      }
    ],
    "list": [
      {
        "operation": "ListMysqlMysqlConfiguration",
        "requestType": "mysql.ListMysqlMysqlConfigurationRequest",
        "responseType": "mysql.ListMysqlMysqlConfigurationResponse"
      }
    ],
    "update": [
      {
        "operation": "UpdateMysqlMysqlConfiguration",
        "requestType": "mysql.UpdateMysqlMysqlConfigurationRequest",
        "responseType": "mysql.UpdateMysqlMysqlConfigurationResponse"
      }
    ],
    "delete": [
      {
        "operation": "DeleteMysqlMysqlConfiguration",
        "requestType": "mysql.DeleteMysqlMysqlConfigurationRequest",
        "responseType": "mysql.DeleteMysqlMysqlConfigurationResponse"
      }
    ]
  },
  "lifecycle": {
    "create": {
      "pending": [
        "PROVISIONING"
      ],
      "target": [
        "ACTIVE"
      ]
    },
    "update": {
      "pending": [
        "UPDATING"
      ],
      "target": [
        "ACTIVE"
      ]
    }
  },
  "mutation": {
    "mutable": [
      "display_name"
    ],
    "forceNew": [
      "compartment_id"
    ],
    "conflictsWith": {}
  },
  "hooks": {
    "create": [
      {
        "helper": "tfresource.CreateResource"
      },
      {
        "helper": "tfresource.WaitForWorkRequestWithErrorHandling",
        "entityType": "template",
        "action": "CREATED"
      }
    ],
    "update": [
      {
        "helper": "tfresource.UpdateResource"
      }
    ],
    "delete": [
      {
        "helper": "tfresource.DeleteResource"
      }
    ]
  },
  "deleteConfirmation": {
    "pending": [
      "DELETING"
    ],
    "target": [
      "DELETED"
    ]
  },
  "listLookup": {
    "datasource": "scaffold_mysql_mysqlmysqlconfiguration",
    "collectionField": "mysqlmysqlconfiguration",
    "responseItemsField": "Items",
    "filterFields": [
      "compartment_id",
      "state"
    ]
  },
  "boundary": {
    "providerFactsOnly": true,
    "repoAuthoredSpecPath": "controllers/mysql/mysqlmysqlconfiguration/spec.cfg",
    "repoAuthoredLogicGapsPath": "controllers/mysql/mysqlmysqlconfiguration/logic-gaps.md",
    "excludedSemantics": [
      "bind-versus-create",
      "secret-output",
      "delete-confirmation"
    ]
  },
  "notes": [
    "Scaffold placeholder for mysql/mysqlmysqlconfiguration; replace imported facts before promoting this row beyond scaffold."
  ]
}
