{
  "schemaVersion": 1,
  "surface": "provider-facts",
  "service": "apmconfig",
  "slug": "apmconfigconfigs",
  "kind": "ApmConfigConfigs",
  "sourceRef": "terraform-provider-oci",
  "providerResource": "oci_apm_config_configs",
  "operations": {
    "create": [
      {
        "operation": "CreateApmConfigConfigs",
        "requestType": "apmconfig.CreateApmConfigConfigsRequest",
        "responseType": "apmconfig.CreateApmConfigConfigsResponse"
      }
    ],
    "get": [
      {
        "operation": "GetApmConfigConfigs",
        "requestType": "apmconfig.GetApmConfigConfigsRequest",
        "responseType": "apmconfig.GetApmConfigConfigsResponse"
      }
    ],
    "list": [
      {
        "operation": "ListApmConfigConfigs",
        "requestType": "apmconfig.ListApmConfigConfigsRequest",
        "responseType": "apmconfig.ListApmConfigConfigsResponse"
      }
    ],
    "update": [
      {
        "operation": "UpdateApmConfigConfigs",
        "requestType": "apmconfig.UpdateApmConfigConfigsRequest",
        "responseType": "apmconfig.UpdateApmConfigConfigsResponse"
      }
    ],
    "delete": [
      {
        "operation": "DeleteApmConfigConfigs",
        "requestType": "apmconfig.DeleteApmConfigConfigsRequest",
        "responseType": "apmconfig.DeleteApmConfigConfigsResponse"
      }
    ]
  },
  "lifecycle": {
    "create": {
      "pending": [
        "PROVISIONING"
      ],
      "target": [
        "ACTIVE"
      ]
    },
    "update": {
      "pending": [
        "UPDATING"
      ],
      "target": [
        "ACTIVE"
      ]
    }
  },
  "mutation": {
    "mutable": [
      "display_name"
    ],
    "forceNew": [
      "compartment_id"
    ],
    "conflictsWith": {}
  },
  "hooks": {
    "create": [
      {
        "helper": "tfresource.CreateResource"
      },
      {
        "helper": "tfresource.WaitForWorkRequestWithErrorHandling",
        "entityType": "template",
        "action": "CREATED"
      }
    ],
    "update": [
      {
        "helper": "tfresource.UpdateResource"
      }
    ],
    "delete": [
      {
        "helper": "tfresource.DeleteResource"
      }
    ]
  },
  "deleteConfirmation": {
    "pending": [
      "DELETING"
    ],
    "target": [
      "DELETED"
    ]
  },
  "listLookup": {
    "datasource": "scaffold_apmconfig_apmconfigconfigs",
    "collectionField": "apmconfigconfigs",
    "responseItemsField": "Items",
    "filterFields": [
      "compartment_id",
      "state"
    ]
  },
  "boundary": {
    "providerFactsOnly": true,
    "repoAuthoredSpecPath": "controllers/apmconfig/apmconfigconfigs/spec.cfg",
    "repoAuthoredLogicGapsPath": "controllers/apmconfig/apmconfigconfigs/logic-gaps.md",
    "excludedSemantics": [
      "bind-versus-create",
      "secret-output",
      "delete-confirmation"
    ]
  },
  "notes": [
    "Scaffold placeholder for apmconfig/apmconfigconfigs; replace imported facts before promoting this row beyond scaffold."
  ]
}
