{
  "schemaVersion": 1,
  "surface": "provider-facts",
  "service": "integration",
  "slug": "integrationintegrationinstance",
  "kind": "IntegrationIntegrationInstance",
  "sourceRef": "terraform-provider-oci",
  "providerResource": "oci_integration_integration_instance",
  "operations": {
    "create": [
      {
        "operation": "CreateIntegrationIntegrationInstance",
        "requestType": "integration.CreateIntegrationIntegrationInstanceRequest",
        "responseType": "integration.CreateIntegrationIntegrationInstanceResponse"
      }
    ],
    "get": [
      {
        "operation": "GetIntegrationIntegrationInstance",
        "requestType": "integration.GetIntegrationIntegrationInstanceRequest",
        "responseType": "integration.GetIntegrationIntegrationInstanceResponse"
      }
    ],
    "list": [
      {
        "operation": "ListIntegrationIntegrationInstance",
        "requestType": "integration.ListIntegrationIntegrationInstanceRequest",
        "responseType": "integration.ListIntegrationIntegrationInstanceResponse"
      }
    ],
    "update": [
      {
        "operation": "UpdateIntegrationIntegrationInstance",
        "requestType": "integration.UpdateIntegrationIntegrationInstanceRequest",
        "responseType": "integration.UpdateIntegrationIntegrationInstanceResponse"
      }
    ],
    "delete": [
      {
        "operation": "DeleteIntegrationIntegrationInstance",
        "requestType": "integration.DeleteIntegrationIntegrationInstanceRequest",
        "responseType": "integration.DeleteIntegrationIntegrationInstanceResponse"
      }
    ]
  },
  "lifecycle": {
    "create": {
      "pending": [
        "PROVISIONING"
      ],
      "target": [
        "ACTIVE"
      ]
    },
    "update": {
      "pending": [
        "UPDATING"
      ],
      "target": [
        "ACTIVE"
      ]
    }
  },
  "mutation": {
    "mutable": [
      "display_name"
    ],
    "forceNew": [
      "compartment_id"
    ],
    "conflictsWith": {}
  },
  "hooks": {
    "create": [
      {
        "helper": "tfresource.CreateResource"
      },
      {
        "helper": "tfresource.WaitForWorkRequestWithErrorHandling",
        "entityType": "template",
        "action": "CREATED"
      }
    ],
    "update": [
      {
        "helper": "tfresource.UpdateResource"
      }
    ],
    "delete": [
      {
        "helper": "tfresource.DeleteResource"
      }
    ]
  },
  "deleteConfirmation": {
    "pending": [
      "DELETING"
    ],
    "target": [
      "DELETED"
    ]
  },
  "listLookup": {
    "datasource": "scaffold_integration_integrationintegrationinstance",
    "collectionField": "integrationintegrationinstance",
    "responseItemsField": "Items",
    "filterFields": [
      "compartment_id",
      "state"
    ]
  },
  "boundary": {
    "providerFactsOnly": true,
    "repoAuthoredSpecPath": "controllers/integration/integrationintegrationinstance/spec.cfg",
    "repoAuthoredLogicGapsPath": "controllers/integration/integrationintegrationinstance/logic-gaps.md",
    "excludedSemantics": [
      "bind-versus-create",
      "secret-output",
      "delete-confirmation"
    ]
  },
  "notes": [
    "Scaffold placeholder for integration/integrationintegrationinstance; replace imported facts before promoting this row beyond scaffold."
  ]
}
