{
  "schemaVersion": 1,
  "surface": "provider-facts",
  "service": "bds",
  "slug": "bdsbdsinstancelistospatches",
  "kind": "BdsBdsInstanceListOsPatches",
  "sourceRef": "terraform-provider-oci",
  "providerResource": "oci_bds_bds_instance_list_os_patches",
  "operations": {
    "create": [
      {
        "operation": "CreateBdsBdsInstanceListOsPatches",
        "requestType": "bds.CreateBdsBdsInstanceListOsPatchesRequest",
        "responseType": "bds.CreateBdsBdsInstanceListOsPatchesResponse"
      }
    ],
    "get": [
      {
        "operation": "GetBdsBdsInstanceListOsPatches",
        "requestType": "bds.GetBdsBdsInstanceListOsPatchesRequest",
        "responseType": "bds.GetBdsBdsInstanceListOsPatchesResponse"
      }
    ],
    "list": [
      {
        "operation": "ListBdsBdsInstanceListOsPatches",
        "requestType": "bds.ListBdsBdsInstanceListOsPatchesRequest",
        "responseType": "bds.ListBdsBdsInstanceListOsPatchesResponse"
      }
    ],
    "update": [
      {
        "operation": "UpdateBdsBdsInstanceListOsPatches",
        "requestType": "bds.UpdateBdsBdsInstanceListOsPatchesRequest",
        "responseType": "bds.UpdateBdsBdsInstanceListOsPatchesResponse"
      }
    ],
    "delete": [
      {
        "operation": "DeleteBdsBdsInstanceListOsPatches",
        "requestType": "bds.DeleteBdsBdsInstanceListOsPatchesRequest",
        "responseType": "bds.DeleteBdsBdsInstanceListOsPatchesResponse"
      }
    ]
  },
  "lifecycle": {
    "create": {
      "pending": [
        "PROVISIONING"
      ],
      "target": [
        "ACTIVE"
      ]
    },
    "update": {
      "pending": [
        "UPDATING"
      ],
      "target": [
        "ACTIVE"
      ]
    }
  },
  "mutation": {
    "mutable": [
      "display_name"
    ],
    "forceNew": [
      "compartment_id"
    ],
    "conflictsWith": {}
  },
  "hooks": {
    "create": [
      {
        "helper": "tfresource.CreateResource"
      },
      {
        "helper": "tfresource.WaitForWorkRequestWithErrorHandling",
        "entityType": "template",
        "action": "CREATED"
      }
    ],
    "update": [
      {
        "helper": "tfresource.UpdateResource"
      }
    ],
    "delete": [
      {
        "helper": "tfresource.DeleteResource"
      }
    ]
  },
  "deleteConfirmation": {
    "pending": [
      "DELETING"
    ],
    "target": [
      "DELETED"
    ]
  },
  "listLookup": {
    "datasource": "scaffold_bds_bdsbdsinstancelistospatches",
    "collectionField": "bdsbdsinstancelistospatches",
    "responseItemsField": "Items",
    "filterFields": [
      "compartment_id",
      "state"
    ]
  },
  "boundary": {
    "providerFactsOnly": true,
    "repoAuthoredSpecPath": "controllers/bds/bdsbdsinstancelistospatches/spec.cfg",
    "repoAuthoredLogicGapsPath": "controllers/bds/bdsbdsinstancelistospatches/logic-gaps.md",
    "excludedSemantics": [
      "bind-versus-create",
      "secret-output",
      "delete-confirmation"
    ]
  },
  "notes": [
    "Scaffold placeholder for bds/bdsbdsinstancelistospatches; replace imported facts before promoting this row beyond scaffold."
  ]
}
