{
  "schemaVersion": 1,
  "surface": "provider-facts",
  "service": "database",
  "slug": "databasemigration",
  "kind": "DatabaseMigration",
  "sourceRef": "terraform-provider-oci",
  "providerResource": "oci_database_migration",
  "operations": {
    "create": [
      {
        "operation": "CreateDatabaseMigration",
        "requestType": "database.CreateDatabaseMigrationRequest",
        "responseType": "database.CreateDatabaseMigrationResponse"
      }
    ],
    "get": [
      {
        "operation": "GetDatabaseMigration",
        "requestType": "database.GetDatabaseMigrationRequest",
        "responseType": "database.GetDatabaseMigrationResponse"
      }
    ],
    "list": [
      {
        "operation": "ListDatabaseMigration",
        "requestType": "database.ListDatabaseMigrationRequest",
        "responseType": "database.ListDatabaseMigrationResponse"
      }
    ],
    "update": [
      {
        "operation": "UpdateDatabaseMigration",
        "requestType": "database.UpdateDatabaseMigrationRequest",
        "responseType": "database.UpdateDatabaseMigrationResponse"
      }
    ],
    "delete": [
      {
        "operation": "DeleteDatabaseMigration",
        "requestType": "database.DeleteDatabaseMigrationRequest",
        "responseType": "database.DeleteDatabaseMigrationResponse"
      }
    ]
  },
  "lifecycle": {
    "create": {
      "pending": [
        "PROVISIONING"
      ],
      "target": [
        "ACTIVE"
      ]
    },
    "update": {
      "pending": [
        "UPDATING"
      ],
      "target": [
        "ACTIVE"
      ]
    }
  },
  "mutation": {
    "mutable": [
      "display_name"
    ],
    "forceNew": [
      "compartment_id"
    ],
    "conflictsWith": {}
  },
  "hooks": {
    "create": [
      {
        "helper": "tfresource.CreateResource"
      },
      {
        "helper": "tfresource.WaitForWorkRequestWithErrorHandling",
        "entityType": "template",
        "action": "CREATED"
      }
    ],
    "update": [
      {
        "helper": "tfresource.UpdateResource"
      }
    ],
    "delete": [
      {
        "helper": "tfresource.DeleteResource"
      }
    ]
  },
  "deleteConfirmation": {
    "pending": [
      "DELETING"
    ],
    "target": [
      "DELETED"
    ]
  },
  "listLookup": {
    "datasource": "scaffold_database_databasemigration",
    "collectionField": "databasemigration",
    "responseItemsField": "Items",
    "filterFields": [
      "compartment_id",
      "state"
    ]
  },
  "boundary": {
    "providerFactsOnly": true,
    "repoAuthoredSpecPath": "controllers/database/databasemigration/spec.cfg",
    "repoAuthoredLogicGapsPath": "controllers/database/databasemigration/logic-gaps.md",
    "excludedSemantics": [
      "bind-versus-create",
      "secret-output",
      "delete-confirmation"
    ]
  },
  "notes": [
    "Scaffold placeholder for database/databasemigration; replace imported facts before promoting this row beyond scaffold."
  ]
}
