{
  "schemaVersion": 1,
  "surface": "provider-facts",
  "service": "database",
  "slug": "databasedbhomepatches",
  "kind": "DatabaseDbHomePatches",
  "sourceRef": "terraform-provider-oci",
  "providerResource": "oci_database_db_home_patches",
  "operations": {
    "create": [
      {
        "operation": "CreateDatabaseDbHomePatches",
        "requestType": "database.CreateDatabaseDbHomePatchesRequest",
        "responseType": "database.CreateDatabaseDbHomePatchesResponse"
      }
    ],
    "get": [
      {
        "operation": "GetDatabaseDbHomePatches",
        "requestType": "database.GetDatabaseDbHomePatchesRequest",
        "responseType": "database.GetDatabaseDbHomePatchesResponse"
      }
    ],
    "list": [
      {
        "operation": "ListDatabaseDbHomePatches",
        "requestType": "database.ListDatabaseDbHomePatchesRequest",
        "responseType": "database.ListDatabaseDbHomePatchesResponse"
      }
    ],
    "update": [
      {
        "operation": "UpdateDatabaseDbHomePatches",
        "requestType": "database.UpdateDatabaseDbHomePatchesRequest",
        "responseType": "database.UpdateDatabaseDbHomePatchesResponse"
      }
    ],
    "delete": [
      {
        "operation": "DeleteDatabaseDbHomePatches",
        "requestType": "database.DeleteDatabaseDbHomePatchesRequest",
        "responseType": "database.DeleteDatabaseDbHomePatchesResponse"
      }
    ]
  },
  "lifecycle": {
    "create": {
      "pending": [
        "PROVISIONING"
      ],
      "target": [
        "ACTIVE"
      ]
    },
    "update": {
      "pending": [
        "UPDATING"
      ],
      "target": [
        "ACTIVE"
      ]
    }
  },
  "mutation": {
    "mutable": [
      "display_name"
    ],
    "forceNew": [
      "compartment_id"
    ],
    "conflictsWith": {}
  },
  "hooks": {
    "create": [
      {
        "helper": "tfresource.CreateResource"
      },
      {
        "helper": "tfresource.WaitForWorkRequestWithErrorHandling",
        "entityType": "template",
        "action": "CREATED"
      }
    ],
    "update": [
      {
        "helper": "tfresource.UpdateResource"
      }
    ],
    "delete": [
      {
        "helper": "tfresource.DeleteResource"
      }
    ]
  },
  "deleteConfirmation": {
    "pending": [
      "DELETING"
    ],
    "target": [
      "DELETED"
    ]
  },
  "listLookup": {
    "datasource": "scaffold_database_databasedbhomepatches",
    "collectionField": "databasedbhomepatches",
    "responseItemsField": "Items",
    "filterFields": [
      "compartment_id",
      "state"
    ]
  },
  "boundary": {
    "providerFactsOnly": true,
    "repoAuthoredSpecPath": "controllers/database/databasedbhomepatches/spec.cfg",
    "repoAuthoredLogicGapsPath": "controllers/database/databasedbhomepatches/logic-gaps.md",
    "excludedSemantics": [
      "bind-versus-create",
      "secret-output",
      "delete-confirmation"
    ]
  },
  "notes": [
    "Scaffold placeholder for database/databasedbhomepatches; replace imported facts before promoting this row beyond scaffold."
  ]
}
