{
  "schemaVersion": 1,
  "surface": "provider-facts",
  "service": "database",
  "slug": "dbversion",
  "kind": "DbVersion",
  "sourceRef": "terraform-provider-oci",
  "providerResource": "scaffold_database_dbversion",
  "operations": {
    "create": [
      {
        "operation": "CreateDbVersion",
        "requestType": "database.CreateDbVersionRequest",
        "responseType": "database.CreateDbVersionResponse"
      }
    ],
    "get": [
      {
        "operation": "GetDbVersion",
        "requestType": "database.GetDbVersionRequest",
        "responseType": "database.GetDbVersionResponse"
      }
    ],
    "list": [
      {
        "operation": "ListDbVersion",
        "requestType": "database.ListDbVersionRequest",
        "responseType": "database.ListDbVersionResponse"
      }
    ],
    "update": [
      {
        "operation": "UpdateDbVersion",
        "requestType": "database.UpdateDbVersionRequest",
        "responseType": "database.UpdateDbVersionResponse"
      }
    ],
    "delete": [
      {
        "operation": "DeleteDbVersion",
        "requestType": "database.DeleteDbVersionRequest",
        "responseType": "database.DeleteDbVersionResponse"
      }
    ]
  },
  "lifecycle": {
    "create": {
      "pending": [
        "PROVISIONING"
      ],
      "target": [
        "ACTIVE"
      ]
    },
    "update": {
      "pending": [
        "UPDATING"
      ],
      "target": [
        "ACTIVE"
      ]
    }
  },
  "mutation": {
    "mutable": [
      "display_name"
    ],
    "forceNew": [
      "compartment_id"
    ],
    "conflictsWith": {}
  },
  "hooks": {
    "create": [
      {
        "helper": "tfresource.CreateResource"
      },
      {
        "helper": "tfresource.WaitForWorkRequestWithErrorHandling",
        "entityType": "template",
        "action": "CREATED"
      }
    ],
    "update": [
      {
        "helper": "tfresource.UpdateResource"
      }
    ],
    "delete": [
      {
        "helper": "tfresource.DeleteResource"
      }
    ]
  },
  "deleteConfirmation": {
    "pending": [
      "DELETING"
    ],
    "target": [
      "DELETED"
    ]
  },
  "listLookup": {
    "datasource": "scaffold_database_dbversion",
    "collectionField": "dbversion",
    "responseItemsField": "Items",
    "filterFields": [
      "compartment_id",
      "state"
    ]
  },
  "boundary": {
    "providerFactsOnly": true,
    "repoAuthoredSpecPath": "controllers/database/dbversion/spec.cfg",
    "repoAuthoredLogicGapsPath": "controllers/database/dbversion/logic-gaps.md",
    "excludedSemantics": [
      "bind-versus-create",
      "secret-output",
      "delete-confirmation"
    ]
  },
  "notes": [
    "Scaffold placeholder for database/dbversion; replace imported facts before promoting this row beyond scaffold."
  ]
}
