{
  "schemaVersion": 1,
  "surface": "provider-facts",
  "service": "datasafe",
  "slug": "datasafediscoveryanalytics",
  "kind": "DataSafeDiscoveryAnalytics",
  "sourceRef": "terraform-provider-oci",
  "providerResource": "oci_data_safe_discovery_analytics",
  "operations": {
    "create": [
      {
        "operation": "CreateDataSafeDiscoveryAnalytics",
        "requestType": "datasafe.CreateDataSafeDiscoveryAnalyticsRequest",
        "responseType": "datasafe.CreateDataSafeDiscoveryAnalyticsResponse"
      }
    ],
    "get": [
      {
        "operation": "GetDataSafeDiscoveryAnalytics",
        "requestType": "datasafe.GetDataSafeDiscoveryAnalyticsRequest",
        "responseType": "datasafe.GetDataSafeDiscoveryAnalyticsResponse"
      }
    ],
    "list": [
      {
        "operation": "ListDataSafeDiscoveryAnalytics",
        "requestType": "datasafe.ListDataSafeDiscoveryAnalyticsRequest",
        "responseType": "datasafe.ListDataSafeDiscoveryAnalyticsResponse"
      }
    ],
    "update": [
      {
        "operation": "UpdateDataSafeDiscoveryAnalytics",
        "requestType": "datasafe.UpdateDataSafeDiscoveryAnalyticsRequest",
        "responseType": "datasafe.UpdateDataSafeDiscoveryAnalyticsResponse"
      }
    ],
    "delete": [
      {
        "operation": "DeleteDataSafeDiscoveryAnalytics",
        "requestType": "datasafe.DeleteDataSafeDiscoveryAnalyticsRequest",
        "responseType": "datasafe.DeleteDataSafeDiscoveryAnalyticsResponse"
      }
    ]
  },
  "lifecycle": {
    "create": {
      "pending": [
        "PROVISIONING"
      ],
      "target": [
        "ACTIVE"
      ]
    },
    "update": {
      "pending": [
        "UPDATING"
      ],
      "target": [
        "ACTIVE"
      ]
    }
  },
  "mutation": {
    "mutable": [
      "display_name"
    ],
    "forceNew": [
      "compartment_id"
    ],
    "conflictsWith": {}
  },
  "hooks": {
    "create": [
      {
        "helper": "tfresource.CreateResource"
      },
      {
        "helper": "tfresource.WaitForWorkRequestWithErrorHandling",
        "entityType": "template",
        "action": "CREATED"
      }
    ],
    "update": [
      {
        "helper": "tfresource.UpdateResource"
      }
    ],
    "delete": [
      {
        "helper": "tfresource.DeleteResource"
      }
    ]
  },
  "deleteConfirmation": {
    "pending": [
      "DELETING"
    ],
    "target": [
      "DELETED"
    ]
  },
  "listLookup": {
    "datasource": "scaffold_datasafe_datasafediscoveryanalytics",
    "collectionField": "datasafediscoveryanalytics",
    "responseItemsField": "Items",
    "filterFields": [
      "compartment_id",
      "state"
    ]
  },
  "boundary": {
    "providerFactsOnly": true,
    "repoAuthoredSpecPath": "controllers/datasafe/datasafediscoveryanalytics/spec.cfg",
    "repoAuthoredLogicGapsPath": "controllers/datasafe/datasafediscoveryanalytics/logic-gaps.md",
    "excludedSemantics": [
      "bind-versus-create",
      "secret-output",
      "delete-confirmation"
    ]
  },
  "notes": [
    "Scaffold placeholder for datasafe/datasafediscoveryanalytics; replace imported facts before promoting this row beyond scaffold."
  ]
}
