{
  "schemaVersion": 1,
  "surface": "provider-facts",
  "service": "core",
  "slug": "image",
  "kind": "Image",
  "sourceRef": "terraform-provider-oci",
  "providerResource": "scaffold_core_image",
  "operations": {
    "create": [
      {
        "operation": "CreateImage",
        "requestType": "core.CreateImageRequest",
        "responseType": "core.CreateImageResponse"
      }
    ],
    "get": [
      {
        "operation": "GetImage",
        "requestType": "core.GetImageRequest",
        "responseType": "core.GetImageResponse"
      }
    ],
    "list": [
      {
        "operation": "ListImage",
        "requestType": "core.ListImageRequest",
        "responseType": "core.ListImageResponse"
      }
    ],
    "update": [
      {
        "operation": "UpdateImage",
        "requestType": "core.UpdateImageRequest",
        "responseType": "core.UpdateImageResponse"
      }
    ],
    "delete": [
      {
        "operation": "DeleteImage",
        "requestType": "core.DeleteImageRequest",
        "responseType": "core.DeleteImageResponse"
      }
    ]
  },
  "lifecycle": {
    "create": {
      "pending": [
        "PROVISIONING"
      ],
      "target": [
        "ACTIVE"
      ]
    },
    "update": {
      "pending": [
        "UPDATING"
      ],
      "target": [
        "ACTIVE"
      ]
    }
  },
  "mutation": {
    "mutable": [
      "display_name"
    ],
    "forceNew": [
      "compartment_id"
    ],
    "conflictsWith": {}
  },
  "hooks": {
    "create": [
      {
        "helper": "tfresource.CreateResource"
      },
      {
        "helper": "tfresource.WaitForWorkRequestWithErrorHandling",
        "entityType": "template",
        "action": "CREATED"
      }
    ],
    "update": [
      {
        "helper": "tfresource.UpdateResource"
      }
    ],
    "delete": [
      {
        "helper": "tfresource.DeleteResource"
      }
    ]
  },
  "deleteConfirmation": {
    "pending": [
      "DELETING"
    ],
    "target": [
      "DELETED"
    ]
  },
  "listLookup": {
    "datasource": "scaffold_core_image",
    "collectionField": "image",
    "responseItemsField": "Items",
    "filterFields": [
      "compartment_id",
      "state"
    ]
  },
  "boundary": {
    "providerFactsOnly": true,
    "repoAuthoredSpecPath": "controllers/core/image/spec.cfg",
    "repoAuthoredLogicGapsPath": "controllers/core/image/logic-gaps.md",
    "excludedSemantics": [
      "bind-versus-create",
      "secret-output",
      "delete-confirmation"
    ]
  },
  "notes": [
    "Scaffold placeholder for core/image; replace imported facts before promoting this row beyond scaffold."
  ]
}
