{
  "schemaVersion": 1,
  "surface": "provider-facts",
  "service": "opsi",
  "slug": "opsinewsreport",
  "kind": "OpsiNewsReport",
  "sourceRef": "terraform-provider-oci",
  "providerResource": "oci_opsi_news_report",
  "operations": {
    "create": [
      {
        "operation": "CreateOpsiNewsReport",
        "requestType": "opsi.CreateOpsiNewsReportRequest",
        "responseType": "opsi.CreateOpsiNewsReportResponse"
      }
    ],
    "get": [
      {
        "operation": "GetOpsiNewsReport",
        "requestType": "opsi.GetOpsiNewsReportRequest",
        "responseType": "opsi.GetOpsiNewsReportResponse"
      }
    ],
    "list": [
      {
        "operation": "ListOpsiNewsReport",
        "requestType": "opsi.ListOpsiNewsReportRequest",
        "responseType": "opsi.ListOpsiNewsReportResponse"
      }
    ],
    "update": [
      {
        "operation": "UpdateOpsiNewsReport",
        "requestType": "opsi.UpdateOpsiNewsReportRequest",
        "responseType": "opsi.UpdateOpsiNewsReportResponse"
      }
    ],
    "delete": [
      {
        "operation": "DeleteOpsiNewsReport",
        "requestType": "opsi.DeleteOpsiNewsReportRequest",
        "responseType": "opsi.DeleteOpsiNewsReportResponse"
      }
    ]
  },
  "lifecycle": {
    "create": {
      "pending": [
        "PROVISIONING"
      ],
      "target": [
        "ACTIVE"
      ]
    },
    "update": {
      "pending": [
        "UPDATING"
      ],
      "target": [
        "ACTIVE"
      ]
    }
  },
  "mutation": {
    "mutable": [
      "display_name"
    ],
    "forceNew": [
      "compartment_id"
    ],
    "conflictsWith": {}
  },
  "hooks": {
    "create": [
      {
        "helper": "tfresource.CreateResource"
      },
      {
        "helper": "tfresource.WaitForWorkRequestWithErrorHandling",
        "entityType": "template",
        "action": "CREATED"
      }
    ],
    "update": [
      {
        "helper": "tfresource.UpdateResource"
      }
    ],
    "delete": [
      {
        "helper": "tfresource.DeleteResource"
      }
    ]
  },
  "deleteConfirmation": {
    "pending": [
      "DELETING"
    ],
    "target": [
      "DELETED"
    ]
  },
  "listLookup": {
    "datasource": "scaffold_opsi_opsinewsreport",
    "collectionField": "opsinewsreport",
    "responseItemsField": "Items",
    "filterFields": [
      "compartment_id",
      "state"
    ]
  },
  "boundary": {
    "providerFactsOnly": true,
    "repoAuthoredSpecPath": "controllers/opsi/opsinewsreport/spec.cfg",
    "repoAuthoredLogicGapsPath": "controllers/opsi/opsinewsreport/logic-gaps.md",
    "excludedSemantics": [
      "bind-versus-create",
      "secret-output",
      "delete-confirmation"
    ]
  },
  "notes": [
    "Scaffold placeholder for opsi/opsinewsreport; replace imported facts before promoting this row beyond scaffold."
  ]
}
