{
  "schemaVersion": 1,
  "surface": "provider-facts",
  "service": "batch",
  "slug": "batchbatchtaskenvironments",
  "kind": "BatchBatchTaskEnvironments",
  "sourceRef": "terraform-provider-oci",
  "providerResource": "oci_batch_batch_task_environments",
  "operations": {
    "create": [
      {
        "operation": "CreateBatchBatchTaskEnvironments",
        "requestType": "batch.CreateBatchBatchTaskEnvironmentsRequest",
        "responseType": "batch.CreateBatchBatchTaskEnvironmentsResponse"
      }
    ],
    "get": [
      {
        "operation": "GetBatchBatchTaskEnvironments",
        "requestType": "batch.GetBatchBatchTaskEnvironmentsRequest",
        "responseType": "batch.GetBatchBatchTaskEnvironmentsResponse"
      }
    ],
    "list": [
      {
        "operation": "ListBatchBatchTaskEnvironments",
        "requestType": "batch.ListBatchBatchTaskEnvironmentsRequest",
        "responseType": "batch.ListBatchBatchTaskEnvironmentsResponse"
      }
    ],
    "update": [
      {
        "operation": "UpdateBatchBatchTaskEnvironments",
        "requestType": "batch.UpdateBatchBatchTaskEnvironmentsRequest",
        "responseType": "batch.UpdateBatchBatchTaskEnvironmentsResponse"
      }
    ],
    "delete": [
      {
        "operation": "DeleteBatchBatchTaskEnvironments",
        "requestType": "batch.DeleteBatchBatchTaskEnvironmentsRequest",
        "responseType": "batch.DeleteBatchBatchTaskEnvironmentsResponse"
      }
    ]
  },
  "lifecycle": {
    "create": {
      "pending": [
        "PROVISIONING"
      ],
      "target": [
        "ACTIVE"
      ]
    },
    "update": {
      "pending": [
        "UPDATING"
      ],
      "target": [
        "ACTIVE"
      ]
    }
  },
  "mutation": {
    "mutable": [
      "display_name"
    ],
    "forceNew": [
      "compartment_id"
    ],
    "conflictsWith": {}
  },
  "hooks": {
    "create": [
      {
        "helper": "tfresource.CreateResource"
      },
      {
        "helper": "tfresource.WaitForWorkRequestWithErrorHandling",
        "entityType": "template",
        "action": "CREATED"
      }
    ],
    "update": [
      {
        "helper": "tfresource.UpdateResource"
      }
    ],
    "delete": [
      {
        "helper": "tfresource.DeleteResource"
      }
    ]
  },
  "deleteConfirmation": {
    "pending": [
      "DELETING"
    ],
    "target": [
      "DELETED"
    ]
  },
  "listLookup": {
    "datasource": "scaffold_batch_batchbatchtaskenvironments",
    "collectionField": "batchbatchtaskenvironments",
    "responseItemsField": "Items",
    "filterFields": [
      "compartment_id",
      "state"
    ]
  },
  "boundary": {
    "providerFactsOnly": true,
    "repoAuthoredSpecPath": "controllers/batch/batchbatchtaskenvironments/spec.cfg",
    "repoAuthoredLogicGapsPath": "controllers/batch/batchbatchtaskenvironments/logic-gaps.md",
    "excludedSemantics": [
      "bind-versus-create",
      "secret-output",
      "delete-confirmation"
    ]
  },
  "notes": [
    "Scaffold placeholder for batch/batchbatchtaskenvironments; replace imported facts before promoting this row beyond scaffold."
  ]
}
