{
  "schemaVersion": 1,
  "surface": "provider-facts",
  "service": "jms",
  "slug": "jmsfleetdrsfiles",
  "kind": "JmsFleetDrsFiles",
  "sourceRef": "terraform-provider-oci",
  "providerResource": "oci_jms_fleet_drs_files",
  "operations": {
    "create": [
      {
        "operation": "CreateJmsFleetDrsFiles",
        "requestType": "jms.CreateJmsFleetDrsFilesRequest",
        "responseType": "jms.CreateJmsFleetDrsFilesResponse"
      }
    ],
    "get": [
      {
        "operation": "GetJmsFleetDrsFiles",
        "requestType": "jms.GetJmsFleetDrsFilesRequest",
        "responseType": "jms.GetJmsFleetDrsFilesResponse"
      }
    ],
    "list": [
      {
        "operation": "ListJmsFleetDrsFiles",
        "requestType": "jms.ListJmsFleetDrsFilesRequest",
        "responseType": "jms.ListJmsFleetDrsFilesResponse"
      }
    ],
    "update": [
      {
        "operation": "UpdateJmsFleetDrsFiles",
        "requestType": "jms.UpdateJmsFleetDrsFilesRequest",
        "responseType": "jms.UpdateJmsFleetDrsFilesResponse"
      }
    ],
    "delete": [
      {
        "operation": "DeleteJmsFleetDrsFiles",
        "requestType": "jms.DeleteJmsFleetDrsFilesRequest",
        "responseType": "jms.DeleteJmsFleetDrsFilesResponse"
      }
    ]
  },
  "lifecycle": {
    "create": {
      "pending": [
        "PROVISIONING"
      ],
      "target": [
        "ACTIVE"
      ]
    },
    "update": {
      "pending": [
        "UPDATING"
      ],
      "target": [
        "ACTIVE"
      ]
    }
  },
  "mutation": {
    "mutable": [
      "display_name"
    ],
    "forceNew": [
      "compartment_id"
    ],
    "conflictsWith": {}
  },
  "hooks": {
    "create": [
      {
        "helper": "tfresource.CreateResource"
      },
      {
        "helper": "tfresource.WaitForWorkRequestWithErrorHandling",
        "entityType": "template",
        "action": "CREATED"
      }
    ],
    "update": [
      {
        "helper": "tfresource.UpdateResource"
      }
    ],
    "delete": [
      {
        "helper": "tfresource.DeleteResource"
      }
    ]
  },
  "deleteConfirmation": {
    "pending": [
      "DELETING"
    ],
    "target": [
      "DELETED"
    ]
  },
  "listLookup": {
    "datasource": "scaffold_jms_jmsfleetdrsfiles",
    "collectionField": "jmsfleetdrsfiles",
    "responseItemsField": "Items",
    "filterFields": [
      "compartment_id",
      "state"
    ]
  },
  "boundary": {
    "providerFactsOnly": true,
    "repoAuthoredSpecPath": "controllers/jms/jmsfleetdrsfiles/spec.cfg",
    "repoAuthoredLogicGapsPath": "controllers/jms/jmsfleetdrsfiles/logic-gaps.md",
    "excludedSemantics": [
      "bind-versus-create",
      "secret-output",
      "delete-confirmation"
    ]
  },
  "notes": [
    "Scaffold placeholder for jms/jmsfleetdrsfiles; replace imported facts before promoting this row beyond scaffold."
  ]
}
